nonebot/adapters/efchat/__init__.py
nonebot/adapters/efchat/adapter.py
nonebot/adapters/efchat/bot.py
nonebot/adapters/efchat/config.py
nonebot/adapters/efchat/event.py
nonebot/adapters/efchat/exception.py
nonebot/adapters/efchat/message.py
nonebot/adapters/efchat/models.py
nonebot/adapters/efchat/rules.py
nonebot/adapters/efchat/utils.py
nonebot_adapter_efchat-0.1.9.post2.dist-info/LICENSE
nonebot_adapter_efchat-0.1.9.post2.dist-info/METADATA
nonebot_adapter_efchat-0.1.9.post2.dist-info/WHEEL
nonebot_adapter_efchat-0.1.9.post2.dist-info/RECORD
