Metadata-Version: 2.3
Name: nonebot-adapter-efchat
Version: 0.1.9.post2
Summary: A NoneBot adapter for EFChat
License: MIT
Keywords: bot,efchat,wtek
Author: molanp
Author-email: molanpp@outlook.com
Requires-Python: >=3.9,<4.0
Classifier: Development Status :: 5 - Production/Stable
Classifier: Framework :: Robot Framework
Classifier: Framework :: Robot Framework :: Library
Classifier: License :: OSI Approved :: MIT License
Classifier: Operating System :: OS Independent
Classifier: Programming Language :: Python :: 3
Classifier: Programming Language :: Python :: 3.9
Classifier: Programming Language :: Python :: 3.10
Classifier: Programming Language :: Python :: 3.11
Classifier: Programming Language :: Python :: 3.12
Classifier: Programming Language :: Python :: 3.13
Requires-Dist: aiofiles (>=23.0.0)
Requires-Dist: filetype (>=1.0.0)
Requires-Dist: nonebot2 (>=2.2.0)
Requires-Dist: pydantic (>=1.10.0,<3.0.0,!=2.5.0,!=2.5.1)
Requires-Dist: typing-extensions (>=4.0.0)
Project-URL: Homepage, https://github.com/molanp/nonebot_adapter_efchat
Project-URL: Repository, https://github.com/molanp/nonebot_adapter_efchat
